snes_scrub/Nintendo - Super Nintendo Entertainment System (20221002-102033).dat
snes_scrub/__init__.py
snes_scrub/scrub.py
snes_scrub-0.1.1.dist-info/LICENSE.txt
snes_scrub-0.1.1.dist-info/METADATA
snes_scrub-0.1.1.dist-info/WHEEL
snes_scrub-0.1.1.dist-info/entry_points.txt
snes_scrub-0.1.1.dist-info/top_level.txt
snes_scrub-0.1.1.dist-info/RECORD
