Metadata-Version: 2.1
Name: snes-scrub
Version: 0.1.1
Summary: Strip SMC headers and rename SNES ROM files using no-intro.org data and naming conventions
Home-page: https://github.com/markmahoney/snes_scrub
Author: Mark Mahoney
Author-email: bcmark@gmail.com
Classifier: Programming Language :: Python
Classifier: Programming Language :: Python :: 3
Classifier: Programming Language :: Python :: 3.9
Requires-Python: >=3
License-File: LICENSE.txt
